{
	"format_version": "1.20.10",
	
	"minecraft:recipe_shaped": {
		"description": {
			"identifier": "minecraft:silence_armor_trim_smithing_template_duplicate"
		},
		
		"tags": ["crafting_table"],
		"unlock": ["minecraft:silence_armor_trim_smithing_template"],
		
		"pattern": [
			"C#C",
			"#S#",
			"C#C"
		],
		"key": {
			"S": "minecraft:silence_armor_trim_smithing_template",
			"#": "minecraft:diamond",
			"C": "minecraft:cobbled_deepslate"
		},
		"result": {"item": "minecraft:silence_armor_trim_smithing_template", "count": 2}
	}
}